{"uuid":"6F231913-BDD0-4524-8DFC-3FE50134D677","midiBankChangeNumber":0,"canDelete":true,"name":"Bank A","presets":[{"isUser":false,"uid":"22870F51-0121-49F3-A162-3C2F4D13C55D","position":0,"bankNumber":0,"programChangeNumber":0,"infoText":"Welcome!","originalUid":"22870F51-0121-49F3-A162-3C2F4D13C55D","parameterValues":[],"version":"1","modWheelDestination":0,"name":"Normal Preset"},{"isUser":false,"uid":"C958DCC3-CD92-46E9-B13F-9BF6463D89C4","position":0,"bankNumber":0,"programChangeNumber":0,"infoText":"Piano + FX","originalUid":"C958DCC3-CD92-46E9-B13F-9BF6463D89C4","parameterValues":[{"value":0.77700001001358032,"identifier":"exampleInstrumentvolumeControl"},{"value":0.30000001192092896,"identifier":"exampleInstrumenttremoloRate"},{"value":0,"identifier":"exampleInstrumenttremoloDepth"},{"value":0,"identifier":"exampleInstrumentphaserEnable"},{"value":0,"identifier":"exampleInstrumentphaserSpeed"},{"value":0.375,"identifier":"exampleInstrumentphaserFeedback"},{"value":0.31034481525421143,"identifier":"exampleInstrumentphaserNotch"},{"value":1,"identifier":"exampleInstrumentautopanEnable"},{"value":0.22250001132488251,"identifier":"exampleInstrumentautopanRate"},{"value":0.25,"identifier":"exampleInstrumentnoiseVolume"},{"value":0,"identifier":"exampleInstrumentrelease"},{"value":0.5,"identifier":"exampleInstrumenttuningSemi"},{"value":0.540000319480896,"identifier":"exampleInstrumentautopanDepth"},{"value":1,"identifier":"exampleInstrumentreverbEnable"},{"value":0.61999994516372681,"identifier":"exampleInstrumentreverbSize"},{"value":0.24750012159347534,"identifier":"exampleInstrumentreverbMix"},{"value":0,"identifier":"exampleInstrumentstereoWiden"},{"value":1,"identifier":"exampleInstrumentnoiseEnable"}],"version":"1","modWheelDestination":0,"name":"80s 4op FM"},{"isUser":false,"uid":"E8AD9872-D333-46FC-889B-B7ECE18F29F8","position":0,"bankNumber":0,"programChangeNumber":0,"infoText":"Basic piano w\/ stereo widening","originalUid":"E8AD9872-D333-46FC-889B-B7ECE18F29F8","parameterValues":[{"value":0.77700001001358032,"identifier":"exampleInstrumentvolumeControl"},{"value":0.30000001192092896,"identifier":"exampleInstrumenttremoloRate"},{"value":0.15749996900558472,"identifier":"exampleInstrumenttremoloDepth"},{"value":0,"identifier":"exampleInstrumentphaserEnable"},{"value":0,"identifier":"exampleInstrumentphaserSpeed"},{"value":0.375,"identifier":"exampleInstrumentphaserFeedback"},{"value":0.31034481525421143,"identifier":"exampleInstrumentphaserNotch"},{"value":0,"identifier":"exampleInstrumentautopanEnable"},{"value":0.25,"identifier":"exampleInstrumentautopanRate"},{"value":0.25,"identifier":"exampleInstrumentnoiseVolume"},{"value":0,"identifier":"exampleInstrumentrelease"},{"value":0.5,"identifier":"exampleInstrumenttuningSemi"},{"value":1,"identifier":"exampleInstrumentautopanDepth"},{"value":1,"identifier":"exampleInstrumentreverbEnable"},{"value":0.5,"identifier":"exampleInstrumentreverbSize"},{"value":0.21000009775161743,"identifier":"exampleInstrumentreverbMix"},{"value":1,"identifier":"exampleInstrumentstereoWiden"},{"value":1,"identifier":"exampleInstrumentnoiseEnable"}],"version":"1","modWheelDestination":0,"name":"Stereo"},{"isUser":false,"uid":"2D6C61EA-911F-4FEA-BC2B-20AA79FCB7C9","position":0,"bankNumber":0,"programChangeNumber":0,"infoText":"Pad sound","originalUid":"2D6C61EA-911F-4FEA-BC2B-20AA79FCB7C9","parameterValues":[{"value":1,"identifier":"exampleInstrumentvolumeControl"},{"value":0.15496404469013214,"identifier":"exampleInstrumenttremoloRate"},{"value":0.15654677152633667,"identifier":"exampleInstrumenttremoloDepth"},{"value":0,"identifier":"exampleInstrumentautopanEnable"},{"value":0.25,"identifier":"exampleInstrumentautopanRate"},{"value":0.56272655725479126,"identifier":"exampleInstrumentattack"},{"value":0.0010000000474974513,"identifier":"exampleInstrumentdecay"},{"value":1,"identifier":"exampleInstrumentsustain"},{"value":0.85524827241897583,"identifier":"exampleInstrumentrelease"},{"value":0.5,"identifier":"exampleInstrumenttuningSemi"},{"value":1,"identifier":"exampleInstrumentautopanDepth"},{"value":1,"identifier":"exampleInstrumentreverbEnable"},{"value":0.84992820024490356,"identifier":"exampleInstrumentreverbSize"},{"value":0.99035972356796265,"identifier":"exampleInstrumentreverbMix"},{"value":0,"identifier":"exampleInstrumentstereoWiden"}],"version":"1","modWheelDestination":0,"name":"St. Paddy"}]}
